__init__.py
gh_secrets_and_vars_async.py
augint_github-1.3.1.dist-info/METADATA
augint_github-1.3.1.dist-info/WHEEL
augint_github-1.3.1.dist-info/entry_points.txt
augint_github-1.3.1.dist-info/RECORD
