Metadata-Version: 2.3
Name: augint-github
Version: 1.3.1
Summary: GitHub tools for Augmenting Integrations
License: AGPL-3.0-only
Author: Samuel Vange
Author-email: 7166607+svange@users.noreply.github.com
Requires-Python: >=3.9,<4.0
Classifier: License :: OSI Approved :: GNU Affero General Public License v3
Classifier: Programming Language :: Python :: 3
Classifier: Programming Language :: Python :: 3.9
Classifier: Programming Language :: Python :: 3.10
Classifier: Programming Language :: Python :: 3.11
Classifier: Programming Language :: Python :: 3.12
Classifier: Programming Language :: Python :: 3.13
Requires-Dist: click (>=8.1.8,<9.0.0)
Requires-Dist: loguru (>=0.7.3,<0.8.0)
Requires-Dist: pygithub (>=2.5.0,<3.0.0)
Requires-Dist: python-dotenv (>=1.0.1,<2.0.0)
Requires-Dist: rich (>=13.9.4,<15.0)
Project-URL: Homepage, https://github.com/svange/augint-github
